shinya/__init__.py
shinya/bd/__init__.py
shinya/bd/clpi.py
shinya/bd/extension_data.py
shinya/bd/indx.py
shinya/bd/mobj.py
shinya/bd/mpls.py
shinya/common/__init__.py
shinya/common/info_dict.py
shinya/common/io.py
shinya/tools/__init__.py
shinya/tools/chapter.py
shinya-0.2a1.dist-info/METADATA
shinya-0.2a1.dist-info/WHEEL
shinya-0.2a1.dist-info/top_level.txt
shinya-0.2a1.dist-info/RECORD
